dframe_utils-0.0.2rc2.dist-info/DESCRIPTION.rst
dframe_utils-0.0.2rc2.dist-info/METADATA
dframe_utils-0.0.2rc2.dist-info/RECORD
dframe_utils-0.0.2rc2.dist-info/WHEEL
dframe_utils-0.0.2rc2.dist-info/metadata.json
dframe_utils-0.0.2rc2.dist-info/top_level.txt
dframeutils/__init__.py
dframeutils/dataframeutils.py
dframeutils/randutils.py
dframeutils/textutils.py
tests/__init__.py
