Metadata-Version: 2.0
Name: dframe-utils
Version: 0.0.2rc2
Summary: simple utility tools for dataframes in Python
Home-page: https://github.com/bharathgs/dframeutils
Author: Bharath G.S
Author-email: royalkingpin@gmail.com
License: MIT
Keywords: Pandas,dataframe,data-cleaning,utility,tidytext,tidydata
Platform: UNKNOWN
Classifier: Development Status :: 4 - Beta
Classifier: Intended Audience :: Developers
Classifier: License :: OSI Approved :: MIT License
Classifier: Natural Language :: English
Classifier: Operating System :: OS Independent
Classifier: Programming Language :: Python :: 3.6
